alu.sv
module alu (output logic signed [31:0] ALUResult,
            output logic Zero, Negative,
            input logic signed [31:0] SrcA, SrcB,
            input logic [4:0] ALUControl);

// Enter your code here

    always @(*) begin

        case (ALUControl)
            5'b10110, 5'b10010, 5'b00010, 5'b00110: ALUResult = SrcA + SrcB;
            5'b11110, 5'b11010, 5'b01010, 5'b01110: ALUResult = SrcA - SrcB;
            5'b00111, 5'b01111, 5'b10111, 5'b11111: ALUResult = SrcA | SrcB;
            5'b00011, 5'b01011, 5'b10011, 5'b11011: ALUResult = SrcA & SrcB;
            
            5'b00000, 5'b00100, 5'b01000, 5'b01100: ALUResult = SrcA << SrcB[4:0];
            5'b10000, 5'b10100, 5'b11000, 5'b11100: ALUResult = SrcA >> SrcB[4:0];
            
            5'b11001, 5'b11101, 5'b01101, 5'b01001: ALUResult = (SrcA < SrcB) ? 32'b1 : 32'b0;
            
        endcase

        Zero = (ALUResult == 32'b0);
        Negative = ALUResult[31];
    end


endmodule

alu_tb.sv
`timescale 1ns/1ps
`include "alu.sv"

module alu_tb;

    // **Inputs**
    logic signed [31:0] SrcA, SrcB;
    logic [4:0] ALUControl;

    // **Outputs**
    logic signed [31:0] ALUResult;
    logic Zero, Negative;

    // **Instantiate ALU module**
    alu dut (
        .ALUResult(ALUResult),
        .Zero(Zero),
        .Negative(Negative),
        .SrcA(SrcA),
        .SrcB(SrcB),
        .ALUControl(ALUControl)
    );

    // **Test sequence**
    initial begin
        $dumpfile("alu_tb.vcd");
        $dumpvars(0, alu_tb);

        // **Test ADD**
        SrcA = 32'd10;
        SrcB = 32'd5;
        ALUControl = 5'b00010;
        #10;
        $display("ADD | SrcA = %0d, SrcB = %0d | ALUResult = %0d", SrcA, SrcB, ALUResult);

        // **Test SUB**
        SrcA = 32'd20;
        SrcB = 32'd5;
        ALUControl = 5'b11110;
        #10;
        $display("SUB | SrcA = %0d, SrcB = %0d | ALUResult = %0d", SrcA, SrcB, ALUResult);

        // **Test OR**
        SrcA = 32'h0F0F0F0F;
        SrcB = 32'hF0F0F0F0;
        ALUControl = 5'b00111;
        #10;
        $display("OR  | SrcA = %h, SrcB = %h | ALUResult = %h", SrcA, SrcB, ALUResult);

        // **Test AND**
        SrcA = 32'h0F0F0F0F;
        SrcB = 32'hF0F0F0F0;
        ALUControl = 5'b00011;
        #10;
        $display("AND | SrcA = %h, SrcB = %h | ALUResult = %h", SrcA, SrcB, ALUResult);

       // **Test Logical Left Shift (SLL)**
        SrcA = 32'h00000002;
        SrcB = 32'h00000002; // shift by 2
        ALUControl = 5'b00000;
        #10;
        $display("SLL | SrcA = %0d, SrcB = %0d | ALUResult = %0d (Expected: 8)", SrcA, SrcB, ALUResult);

        // **Test Logical Right Shift (SRL)**
        SrcA = 32'h00000080;
        SrcB = 32'h00000003; // shift by 3
        ALUControl = 5'b10000;
        #10;
        $display("SRL | SrcA = %0d, SrcB = %0d | ALUResult = %0d (Expected: 16)", SrcA, SrcB, ALUResult);

        // **Test Zero flag**
        SrcA = 32'd10;
        SrcB = 32'd10;
        ALUControl = 5'b11110; // 10 - 10 = 0
        #10;
        $display("ZERO TEST | SrcA = %0d, SrcB = %0d | ALUResult = %0d | Zero = %b", SrcA, SrcB, ALUResult, Zero);

        // **Test Negative flag**
        SrcA = 32'd5;
        SrcB = 32'd10;
        ALUControl = 5'b11110; // 5 - 10 = -5
        #10;
        $display("NEGATIVE TEST | SrcA = %0d, SrcB = %0d | ALUResult = %0d | Negative = %b", SrcA, SrcB, ALUResult, Negative);

        // **End simulation**
        #50;
        $finish;
    end

    // **Monitor ALU computations**
    initial begin
        $monitor("t = %3d | ALUControl = %b | SrcA = %0d (%h) | SrcB = %0d (%h) | ALUResult = %0d (%h) | Zero = %b | Negative = %b", 
                  $time, ALUControl, SrcA, SrcA, SrcB, SrcB, ALUResult, ALUResult, Zero, Negative);
    end

endmodule

alu_tb.vcd
$date
	Fri Mar 21 21:44:07 2025
$end
$version
	Icarus Verilog
$end
$timescale
	1ps
$end
$scope module alu_tb $end
$var wire 1 ! Zero $end
$var wire 1 " Negative $end
$var wire 32 # ALUResult [31:0] $end
$var reg 5 $ ALUControl [4:0] $end
$var reg 32 % SrcA [31:0] $end
$var reg 32 & SrcB [31:0] $end
$scope module dut $end
$var wire 5 ' ALUControl [4:0] $end
$var wire 32 ( SrcA [31:0] $end
$var wire 32 ) SrcB [31:0] $end
$var reg 32 * ALUResult [31:0] $end
$var reg 1 " Negative $end
$var reg 1 ! Zero $end
$upscope $end
$upscope $end
$enddefinitions $end
#0
$dumpvars
b1111 *
b101 )
b1010 (
b10 '
b101 &
b1010 %
b10 $
b1111 #
0"
0!
$end
#10000
b11110 $
b11110 '
b10100 %
b10100 (
#20000
1"
b11111111111111111111111111111111 #
b11111111111111111111111111111111 *
b111 $
b111 '
b11110000111100001111000011110000 &
b11110000111100001111000011110000 )
b1111000011110000111100001111 %
b1111000011110000111100001111 (
#30000
0"
1!
b0 #
b0 *
b11 $
b11 '
#40000
0!
b1000 #
b1000 *
b0 $
b0 '
b10 &
b10 )
b10 %
b10 (
#50000
b10000 #
b10000 *
b10000 $
b10000 '
b11 &
b11 )
b10000000 %
b10000000 (
#60000
1!
b0 #
b0 *
b11110 $
b11110 '
b1010 &
b1010 )
b1010 %
b1010 (
#70000
1"
0!
b11111111111111111111111111111011 #
b11111111111111111111111111111011 *
b101 %
b101 (
