control_unit.sv
module control_unit (output logic [1:0] PCSrc, 
                    output logic [1:0] ResultSrc,
                    output logic MemWrite, ALUSrc, RegWrite,
                    output logic [4:0] ALUControl,
                    output logic [2:0] ImmSrc,
                    input logic [31:0] Instr,
                    input logic Zero, Negative);

// Enter your code here

    logic [6:0] opcode;
    logic [2:0] funct3;
    logic [6:0] funct7;

    assign opcode = Instr[6:0];   // Opcode: 
    assign funct3 = Instr[14:12]; // Funct3: 
    assign funct7 = Instr[31:25]; // Funct7: R 

    // **1. Immsrc**
    always_comb begin
        case (opcode)
            7'b0000011: ImmSrc = 3'b000; // I (LW)
            7'b0010011: ImmSrc = 3'b000; // I (Arithmetic)
            7'b1100111: ImmSrc = 3'b000; // I (JALR)
            7'b0100011: ImmSrc = 3'b001; // S (SW)
            7'b1100011: ImmSrc = 3'b010; // B (Branch)
            7'b0110111: ImmSrc = 3'b011; // U (LUI)
            7'b1101111: ImmSrc = 3'b100; // J (JAL)
            default: ImmSrc = 3'b000;    
        endcase
    end

    // **2. PCSrc**
    always_comb begin
        case (opcode)
            7'b1100011: // (BEQ, BNE, BLT, BGE)
                PCSrc = (funct3 == 3'b000 && Zero)  ? 2'b01 :  // BEQ
                        (funct3 == 3'b001 && !Zero) ? 2'b01 :  // BNE
                        (funct3 == 3'b100 && Negative) ? 2'b01 : // BLT
                        (funct3 == 3'b101 && !Negative) ? 2'b01 : // BGE
                        2'b00; 
            7'b1101111: PCSrc = 2'b01; // JAL
            7'b1100111: PCSrc = 2'b10; // JALR 
            default: PCSrc = 2'b00; 
        endcase
    end

    // **3. ResultSrc**
    always_comb begin
        case (opcode)
            7'b0000011: ResultSrc = 2'b10; // LW 
            7'b1101111: ResultSrc = 2'b11; // JAL 
            7'b1100111: ResultSrc = 2'b11; // JALR (PC+4)
            7'b0110111: ResultSrc = 2'b00; // LUI 
            7'b0010011, 
            7'b0110011: ResultSrc = 2'b01; // I & R
            default: ResultSrc = 2'b00;    
        endcase
    end

    // **4. ALUSrc**
    assign ALUSrc = (opcode == 7'b0010011 ||  // I (Arithmetic)
                     opcode == 7'b0000011 ||  // I (LW)
                     opcode == 7'b0100011 ||  // S (SW)
                     opcode == 7'b1100111);   // I (JALR)

    // **5. MemWrite**
    assign MemWrite = (opcode == 7'b0100011); // SW 

    // **6. RegWrite**
    assign RegWrite = (opcode == 7'b0110011 ||  // R 
                       opcode == 7'b0010011 ||  // I 
                       opcode == 7'b0000011 ||  // LW
                       opcode == 7'b1101111 ||  // JAL
                       opcode == 7'b1100111 ||  // JALR
                       opcode == 7'b0110111);   // LUI

    // **7. ALUControl**
    always_comb begin
        case (opcode)
            7'b0110011: begin // **R 
                case ({funct7, funct3})
                    10'b0000000000: ALUControl = 5'b00110; // ADD
                    10'b0100000000: ALUControl = 5'b01010; // SUB
                    10'b0000000110: ALUControl = 5'b00111; // OR
                    10'b0000000111: ALUControl = 5'b00011; // AND
                    10'b0000000001: ALUControl = 5'b00000; // SLL
                    10'b0000000101: ALUControl = 5'b10000; // SRL
                    10'b0000000010: ALUControl = 5'b01001; // SLT
                    default: ALUControl = 5'b00000; // 
                endcase
            end

            7'b0010011: begin // **I
                case (funct3)
                    3'b000: ALUControl = 5'b00110; // ADDI
                    3'b110: ALUControl = 5'b00111; // ORI
                    3'b111: ALUControl = 5'b00011; // ANDI
                    3'b001: ALUControl = 5'b00000; // SLLI
                    3'b101: ALUControl = 5'b10000; // SRLI
                    3'b010: ALUControl = 5'b01001; // SLTI
                    default: ALUControl = 5'b00000;
                endcase
            end

            7'b0000011, // **LW** 
            7'b0100011, // **SW** 
            7'b1100111: // **JALR**
                ALUControl = 5'b00110; 

            7'b1100011: begin // **Branch**
                case (funct3)
                    3'b000, // BEQ
                    3'b001, // BNE
                    3'b100, // BLT
                    3'b101: // BGE
                        ALUControl = 5'b01010; 
                    default: ALUControl = 5'b00000;
                endcase
            end

            7'b1101111: ALUControl = 5'b00000; // JAL
            7'b0110111: ALUControl = 5'b00000; // LUI

            default: ALUControl = 5'b00000; 
        endcase
    end



endmodule

control_unit_tb.sv
`timescale 1ns/1ps
`include "control_unit.sv"

module control_unit_tb;

  // Inputs
  logic [31:0] Instr;
  logic Zero, Negative;

  // Outputs
  logic [1:0] PCSrc, ResultSrc;
  logic MemWrite, ALUSrc, RegWrite;
  logic [4:0] ALUControl;
  logic [2:0] ImmSrc;

  // Instantiate the DUT (Device Under Test)
  control_unit dut (
    .PCSrc(PCSrc),
    .ResultSrc(ResultSrc),
    .MemWrite(MemWrite),
    .ALUSrc(ALUSrc),
    .RegWrite(RegWrite),
    .ALUControl(ALUControl),
    .ImmSrc(ImmSrc),
    .Instr(Instr),
    .Zero(Zero),
    .Negative(Negative)
  );

  // Test sequence
  initial begin
    $dumpfile("control_unit_tb.vcd");
    $dumpvars(0, control_unit_tb);

    // Test Case 1: R-type (ADD x5, x6, x7) - opcode: 0110011, funct3: 000, funct7: 0000000
    Instr = 32'b0000000_00110_00111_000_00101_0110011; 
    Zero = 0; Negative = 0; #10;
    $display("R-type (ADD) | PCSrc = %b, ALUControl = %b, RegWrite = %b", PCSrc, ALUControl, RegWrite);

    // Test Case 2: I-type (ADDI x5, x6, 10) - opcode: 0010011, funct3: 000
    Instr = 32'b000000000101_00110_000_00101_0010011;
    Zero = 0; Negative = 0; #10;
    $display("I-type (ADDI) | ALUSrc = %b, ALUControl = %b, RegWrite = %b", ALUSrc, ALUControl, RegWrite);

    // Test Case 3: Load Word (LW x5, 0(x6)) - opcode: 0000011, funct3: 010
    Instr = 32'b000000000000_00110_010_00101_0000011;
    Zero = 0; Negative = 0; #10;
    $display("LW | ResultSrc = %b, MemWrite = %b, RegWrite = %b", ResultSrc, MemWrite, RegWrite);

    // Test Case 4: Store Word (SW x5, 0(x6)) - opcode: 0100011, funct3: 010
    Instr = 32'b0000000_00101_00110_010_00000_0100011;
    Zero = 0; Negative = 0; #10;
    $display("SW | MemWrite = %b, ALUSrc = %b", MemWrite, ALUSrc);

    // Test Case 5: Branch if Equal (BEQ x5, x6, offset) - opcode: 1100011, funct3: 000
    Instr = 32'b0000000_00101_00110_000_00000_1100011;
    Zero = 1; Negative = 0; #10;
    $display("BEQ | PCSrc = %b", PCSrc);

    // Test Case 6: Branch if Less Than (BLT x5, x6, offset) - opcode: 1100011, funct3: 100
    Instr = 32'b0000000_00101_00110_100_00000_1100011;
    Zero = 0; Negative = 1; #10;
    $display("BLT | PCSrc = %b", PCSrc);

    // Test Case 7: JAL (Jump and Link) - opcode: 1101111
    Instr = 32'b00000000000000000000_00000_1101111;
    Zero = 0; Negative = 0; #10;
    $display("JAL | PCSrc = %b, RegWrite = %b", PCSrc, RegWrite);

    // Test Case 8: JALR (Jump and Link Register) - opcode: 1100111
    Instr = 32'b000000000000_00001_000_00000_1100111;
    Zero = 0; Negative = 0; #10;
    $display("JALR | PCSrc = %b, RegWrite = %b", PCSrc, RegWrite);

    // Test Case 9: LUI (Load Upper Immediate) - opcode: 0110111
    Instr = 32'b00000000000000000000_00000_0110111;
    Zero = 0; Negative = 0; #10;
    $display("LUI | ResultSrc = %b, RegWrite = %b", ResultSrc, RegWrite);

    // End test
    #50;
    $finish;
  end

  // Monitor values
  initial begin
    $monitor("t = %3d | Instr = %b | PCSrc = %b | ResultSrc = %b | ALUSrc = %b | ALUControl = %b | RegWrite = %b | MemWrite = %b | ImmSrc = %b", 
              $time, Instr, PCSrc, ResultSrc, ALUSrc, ALUControl, RegWrite, MemWrite, ImmSrc);
  end

endmodule

control_unit_tb.vcd
$date
	Fri Mar 21 22:03:32 2025
$end
$version
	Icarus Verilog
$end
$timescale
	1ps
$end
$scope module control_unit_tb $end
$var wire 2 ! ResultSrc [1:0] $end
$var wire 1 " RegWrite $end
$var wire 2 # PCSrc [1:0] $end
$var wire 1 $ MemWrite $end
$var wire 3 % ImmSrc [2:0] $end
$var wire 1 & ALUSrc $end
$var wire 5 ' ALUControl [4:0] $end
$var reg 32 ( Instr [31:0] $end
$var reg 1 ) Negative $end
$var reg 1 * Zero $end
$scope module dut $end
$var wire 1 & ALUSrc $end
$var wire 32 + Instr [31:0] $end
$var wire 1 ) Negative $end
$var wire 1 " RegWrite $end
$var wire 1 * Zero $end
$var wire 7 , opcode [6:0] $end
$var wire 7 - funct7 [6:0] $end
$var wire 3 . funct3 [2:0] $end
$var wire 1 $ MemWrite $end
$var reg 5 / ALUControl [4:0] $end
$var reg 3 0 ImmSrc [2:0] $end
$var reg 2 1 PCSrc [1:0] $end
$var reg 2 2 ResultSrc [1:0] $end
$upscope $end
$upscope $end
$enddefinitions $end
#0
$dumpvars
b1 2
b0 1
b0 0
b110 /
b0 .
b0 -
b110011 ,
b11000111000001010110011 +
0*
0)
b11000111000001010110011 (
b110 '
0&
b0 %
0$
b0 #
1"
b1 !
$end
#10000
1&
b10011 ,
b10100110000001010010011 (
b10100110000001010010011 +
#20000
b10 !
b10 2
b11 ,
b10 .
b110010001010000011 (
b110010001010000011 +
#30000
0"
b0 !
b0 2
b1 %
b1 0
1$
b100011 ,
b10100110010000000100011 (
b10100110010000000100011 +
#40000
0&
b1010 '
b1010 /
b10 %
b10 0
b1 #
b1 1
0$
b1100011 ,
b0 .
1*
b10100110000000001100011 (
b10100110000000001100011 +
#50000
b100 .
1)
0*
b10100110100000001100011 (
b10100110100000001100011 +
#60000
1"
b11 !
b11 2
b0 '
b0 /
b100 %
b100 0
b1101111 ,
b0 .
0)
b1101111 (
b1101111 +
#70000
1&
b110 '
b110 /
b0 %
b0 0
b10 #
b10 1
b1100111 ,
b1000000001100111 (
b1000000001100111 +
#80000
0&
b0 '
b0 /
b0 !
b0 2
b11 %
b11 0
b0 #
b0 1
b110111 ,
b110111 (
b110111 +
