program_counter.sv
module program_counter (output logic [31:0] PC, PCPlus4,
                        input logic [31:0] PCTarget, ALUResult,
                        input logic [1:0] PCSrc, 
                        input logic Reset, CLK);

// Enter your code here

    assign PCPlus4 = PC + 4;

    // Synchronous PC update with reset
    always_ff @(posedge CLK or posedge Reset) begin
        if (Reset) begin
            PC <= 32'b0;  // Reset PC to 0 (start executing from 0x00000000)
        end else begin
            case (PCSrc)
                2'b00: PC <= PCPlus4;   // Sequential execution (PC + 4)
                2'b01: PC <= PCTarget;  // Branch target address
                2'b10: PC <= ALUResult; // JALR computed target
                default: PC <= PCPlus4; // Default case: fall back to sequential
            endcase
        end
    end

endmodule

program_counter_tb.sv
`timescale 1ns/1ps
`include "program_counter.sv"

module program_counter_tb;

  // Inputs
  logic CLK;
  logic Reset;
  logic [1:0] PCSrc;
  logic [31:0] PCTarget, ALUResult;

  // Outputs
  logic [31:0] PC, PCPlus4;

  // Instantiate the `program_counter` module
  program_counter dut (
    .PC(PC),
    .PCPlus4(PCPlus4),
    .PCTarget(PCTarget),
    .ALUResult(ALUResult),
    .PCSrc(PCSrc),
    .Reset(Reset),
    .CLK(CLK)
  );

  // Clock generation (Toggle every 10ns, 20ns period)
  initial begin
    CLK = 0;
    forever #10 CLK = ~CLK;
  end

  // Stimulus
  initial begin
    $dumpfile("program_counter_tb.vcd");
    $dumpvars(0, program_counter_tb);

    // Initialize inputs
    Reset = 1; PCSrc = 2'b00; 
    PCTarget = 32'h00000020;  // Example branch target address
    ALUResult = 32'h00000040; // Example JALR computed address
    
    // Apply Reset
    #20 Reset = 0;  

    // Test vector 1: Sequential Execution (PC + 4)
    PCSrc = 2'b00; #20;
    $display("PC = %h, Expected = 4 | PCPlus4 = %h, Expected = 8", PC, PCPlus4);

    // Test vector 2: Branch Target (PCTarget)
    PCSrc = 2'b01; #20;
    $display("PC = %h, Expected = %h | PCPlus4 = %h (unchanged)", PC, PCTarget, PCPlus4);

    // Test vector 3: JALR (ALUResult)
    PCSrc = 2'b10; #20;
    $display("PC = %h, Expected = %h | PCPlus4 = %h (unchanged)", PC, ALUResult, PCPlus4);

    // Test vector 4: Reset
    Reset = 1; #20;
    Reset = 0;
    $display("PC = %h, Expected = 0 | PCPlus4 = 4", PC, PCPlus4);

    // Additional test cases
    #20 PCSrc = 2'b00; #20;
    #20 PCSrc = 2'b01; PCTarget = 32'h00000050; #20;
    #20 PCSrc = 2'b10; ALUResult = 32'h00000080; #20;
    #20 PCSrc = 2'b00; #20;

    // Allow some additional time for simulation
    #100;
    $finish;
  end

  // Monitor PC and other signals
  initial begin
    $monitor("t = %3d, CLK = %b, Reset = %b, PCSrc = %b, PCTarget = %h, ALUResult = %h, PC = %h, PCPlus4 = %h", 
              $time, CLK, Reset, PCSrc, PCTarget, ALUResult, PC, PCPlus4);
  end

endmodule

program_counter_tb.vcd
$date
	Thu Mar 20 09:19:41 2025
$end
$version
	Icarus Verilog
$end
$timescale
	1ps
$end
$scope module program_counter_tb $end
$var wire 32 ! PCPlus4 [31:0] $end
$var wire 32 " PC [31:0] $end
$var reg 32 # ALUResult [31:0] $end
$var reg 1 $ CLK $end
$var reg 2 % PCSrc [1:0] $end
$var reg 32 & PCTarget [31:0] $end
$var reg 1 ' Reset $end
$scope module dut $end
$var wire 32 ( ALUResult [31:0] $end
$var wire 1 $ CLK $end
$var wire 2 ) PCSrc [1:0] $end
$var wire 32 * PCTarget [31:0] $end
$var wire 1 ' Reset $end
$var wire 32 + PCPlus4 [31:0] $end
$var reg 32 , PC [31:0] $end
$upscope $end
$upscope $end
$enddefinitions $end
#0
$dumpvars
b0 ,
b100 +
b100000 *
b0 )
b1000000 (
1'
b100000 &
b0 %
0$
b1000000 #
b0 "
b100 !
$end
#10000
1$
#20000
0$
0'
#30000
b1000 !
b1000 +
b100 "
b100 ,
1$
#40000
0$
b1 %
b1 )
#50000
b100100 !
b100100 +
b100000 "
b100000 ,
1$
#60000
0$
b10 %
b10 )
#70000
b1000100 !
b1000100 +
b1000000 "
b1000000 ,
1$
#80000
b100 !
b100 +
b0 "
b0 ,
0$
1'
#90000
1$
#100000
0$
0'
#110000
b1000100 !
b1000100 +
b1000000 "
b1000000 ,
1$
#120000
0$
b0 %
b0 )
#130000
b1001000 !
b1001000 +
b1000100 "
b1000100 ,
1$
#140000
0$
#150000
b1001100 !
b1001100 +
b1001000 "
b1001000 ,
1$
#160000
0$
b1010000 &
b1010000 *
b1 %
b1 )
#170000
b1010100 !
b1010100 +
b1010000 "
b1010000 ,
1$
#180000
0$
#190000
1$
#200000
0$
b10000000 #
b10000000 (
b10 %
b10 )
#210000
b10000100 !
b10000100 +
b10000000 "
b10000000 ,
1$
#220000
0$
#230000
1$
#240000
0$
b0 %
b0 )
#250000
b10001000 !
b10001000 +
b10000100 "
b10000100 ,
1$
#260000
0$
#270000
b10001100 !
b10001100 +
b10001000 "
b10001000 ,
1$
#280000
0$
#290000
b10010000 !
b10010000 +
b10001100 "
b10001100 ,
1$
#300000
0$
#310000
b10010100 !
b10010100 +
b10010000 "
b10010000 ,
1$
#320000
0$
#330000
b10011000 !
b10011000 +
b10010100 "
b10010100 ,
1$
#340000
0$
#350000
b10011100 !
b10011100 +
b10011000 "
b10011000 ,
1$
